rewarduq/__init__.py
rewarduq-0.0.0.dist-info/METADATA
rewarduq-0.0.0.dist-info/WHEEL
rewarduq-0.0.0.dist-info/top_level.txt
rewarduq-0.0.0.dist-info/RECORD
