Metadata-Version: 2.4
Name: rewarduq
Version: 0.0.0
Summary: Coming soon
Author-email: Lena Libon <llibon@ethz.ch>, Florian Redhardt <fredhardt@ethz.ch>, Samuel Stante <sstante@ethz.ch>, Daniel Yang <daniel.yang@inf.ethz.ch>
Requires-Python: >=3.9
